genbit.py
dnaseq_genbit-0.0.1.dist-info/LICENSE
dnaseq_genbit-0.0.1.dist-info/METADATA
dnaseq_genbit-0.0.1.dist-info/WHEEL
dnaseq_genbit-0.0.1.dist-info/top_level.txt
dnaseq_genbit-0.0.1.dist-info/RECORD
