Metadata-Version: 2.1
Name: dnaseq-genbit
Version: 0.0.1
Summary: Computationally operate on DNA and RNA sequences
Author: Akhilesh Balaji
Classifier: Programming Language :: Python :: 3
Classifier: License :: OSI Approved :: MIT License
Classifier: Operating System :: OS Independent
Requires-Python: >=3.8
License-File: LICENSE
Requires-Dist: rich
